{
  "Typography": {
    "Title-Color": {
      "value": "{System Label.Dark | Primary}",
      "type": "color"
    },
    "Subtitle-Color": {
      "value": "{System Label.Dark | Secondary}",
      "type": "color"
    },
    "Placeholder-Color": {
      "value": "{System Label.Dark | Tertiary}",
      "type": "color"
    },
    "Disabled-Color": {
      "value": "{System Label.Dark | Quarternary}",
      "type": "color"
    }
  },
  "Page Background": {
    "Secondary": {
      "value": "{System Background.Dark | Secondary}",
      "type": "color"
    },
    "Primery": {
      "value": "{System Background.Dark | Primary}",
      "type": "color"
    },
    "Tertiary": {
      "value": "{System Background.Dark | Teritary}",
      "type": "color"
    }
  },
  "System": {
    "Color": {
      "CTA": {
        "value": "{System Color.Dark | Brand}",
        "type": "color"
      },
      "Error-Color": {
        "value": "{System Color.Dark | Red}",
        "type": "color"
      }
    },
    "Fill": {
      "Primary - Color": {
        "value": "{System Fill Color.Dark | Primary}",
        "type": "color"
      },
      "Secondary - Color": {
        "value": "{System Fill Color.Dark | Secondary}",
        "type": "color"
      },
      "Tertiary - Color": {
        "value": "{System Fill Color.Dark |Tertiary}",
        "type": "color"
      },
      "Quarternary - Color": {
        "value": "{System Fill Color.Dark | Quarternary}",
        "type": "color"
      }
    },
    "Separator": {
      "Opaque": {
        "value": "{System Separator.Dark | Opaque}",
        "type": "color"
      },
      "Non-Opaque": {
        "value": "{System Separator.Dark | Non-Opaque}",
        "type": "color"
      }
    },
    "Gray": {
      "White": {
        "value": "#ffffff",
        "type": "color"
      },
      "Black": {
        "value": "#000000",
        "type": "color"
      },
      "Gray 1": {
        "value": "#909294",
        "type": "color"
      },
      "Gray 2": {
        "value": "#7c7e81",
        "type": "color"
      },
      "Gray 3": {
        "value": "#6e6f72",
        "type": "color"
      },
      "Gray 4": {
        "value": "#626467",
        "type": "color"
      },
      "Gray 5": {
        "value": "#545658",
        "type": "color"
      },
      "Gray 6": {
        "value": "#464749",
        "type": "color"
      },
      "Gray 7": {
        "value": "#38393a",
        "type": "color"
      },
      "Gray 8": {
        "value": "#2d2d2f",
        "type": "color"
      },
      "Gray 9": {
        "value": "#222324",
        "type": "color"
      },
      "Gray 10": {
        "value": "#171718",
        "type": "color"
      }
    }
  },
  "UI Elements Background": {
    "Search Background - Color": {
      "value": "{System Fill Color.Dark |Tertiary}",
      "type": "color"
    }
  },
  "Icon": {
    "Primary-Color": {
      "value": "{System Label.Dark | Primary}",
      "type": "color"
    },
    "Secondary-Color": {
      "value": "{System Label.Dark | Secondary}",
      "type": "color"
    },
    "Tertiary-Color": {
      "value": "{System Label.Dark | Tertiary}",
      "type": "color"
    },
    "Disabled-Color": {
      "value": "{System Label.Dark | Quarternary}",
      "type": "color"
    }
  },
  "Avatar": {
    "Back - Red": {
      "value": "#f16653",
      "type": "color"
    },
    "Back - Purpul": {
      "value": "#f16653",
      "type": "color"
    },
    "Back - Yellow": {
      "value": "#f5cf05",
      "type": "color"
    },
    "Back - Cyan": {
      "value": "#48c2c2",
      "type": "color"
    },
    "Back - Orange": {
      "value": "#f29450",
      "type": "color"
    },
    "Back - Blue": {
      "value": "#719df1",
      "type": "color"
    },
    "Back - Pink": {
      "value": "#de8edf",
      "type": "color"
    },
    "Back - Violet": {
      "value": "#b9a3f8",
      "type": "color"
    },
    "Back - Green": {
      "value": "#72bf44",
      "type": "color"
    },
    "On Back - Red": {
      "value": "#26110d",
      "type": "color"
    },
    "On Back - Puple": {
      "value": "#1d1d2f",
      "type": "color"
    },
    "On Back - Yellow": {
      "value": "#2b2502",
      "type": "color"
    },
    "On Back - Cyan": {
      "value": "#0f2727",
      "type": "color"
    },
    "On Back - Orange": {
      "value": "#29180c",
      "type": "color"
    },
    "On Back - Blue": {
      "value": "#151e2d",
      "type": "color"
    },
    "On Back - Pink": {
      "value": "#2e152e",
      "type": "color"
    },
    "On Back - Violet": {
      "value": "#241c35",
      "type": "color"
    },
    "On Back - Green": {
      "value": "#182b0c",
      "type": "color"
    }
  }
}